quant1x_trader-0.8.18.dist-info/licenses/LICENSE
trader1x/__init__.py
trader1x/config.py
trader1x/context.py
trader1x/log4py.py
trader1x/proxy.py
trader1x/thinktrader.py
trader1x/utils.py
trader1x/win32serviceutil.py
quant1x_trader-0.8.18.dist-info/METADATA
quant1x_trader-0.8.18.dist-info/WHEEL
quant1x_trader-0.8.18.dist-info/entry_points.txt
quant1x_trader-0.8.18.dist-info/top_level.txt
quant1x_trader-0.8.18.dist-info/RECORD
