Metadata-Version: 2.4
Name: quant1x-trader
Version: 0.8.18
Summary: Quant1X程序化自动化交易
Home-page: https://gitee.com/quant1x/trader
Author: WangFeng
Author-email: wangfengxy@sina.cn
License: MIT license
Keywords: quant1x auto trader
Classifier: Development Status :: 2 - Pre-Alpha
Classifier: Intended Audience :: Developers
Classifier: License :: OSI Approved :: MIT License
Classifier: Natural Language :: English
Classifier: Programming Language :: Python :: 3
Classifier: Programming Language :: Python :: 3.8
Classifier: Programming Language :: Python :: 3.9
Classifier: Programming Language :: Python :: 3.10
Classifier: Programming Language :: Python :: 3.11
Classifier: Programming Language :: Python :: 3.12
License-File: LICENSE
Requires-Dist: setuptools~=78.0.0
Requires-Dist: future~=1.0.0
Requires-Dist: numpy~=2.3.0
Requires-Dist: pandas~=2.3.0
Requires-Dist: PyYAML~=6.0.1
Requires-Dist: pywin32==311
Requires-Dist: uvicorn~=0.29.0
Requires-Dist: fastapi~=0.110.2
Requires-Dist: path~=16.14.0
Requires-Dist: requests~=2.32.0
Requires-Dist: loguru~=0.7.2
Requires-Dist: quant1x-xtquant~=2025.5.26
Requires-Dist: quant1x-base~=0.6.29
Requires-Dist: aiohttp~=3.12.15
Requires-Dist: sanic~=23.12.1
Requires-Dist: python-multipart~=0.0.19
Requires-Dist: APScheduler~=3.10.4
Dynamic: author
Dynamic: author-email
Dynamic: classifier
Dynamic: description
Dynamic: home-page
Dynamic: keywords
Dynamic: license
Dynamic: license-file
Dynamic: requires-dist
Dynamic: summary
